{"Workouts": [
  {
    "Name": "Default Chest",
    "Tags": ["chest"],
    "Exercises": ["Bench Press", "Incline Press", "Incline Fly"]
  },
  {
    "Name": "Default Chest2",
    "Tags": ["chest"],
    "Exercises": ["Incline Press"]
  },
  {
    "Name": "Default Back",
    "Tags": ["back"],
    "Exercises": ["Back Row"]
  },
  {
    "Name": "Default Leg",
    "Tags": ["leg"],
    "Exercises": ["Back Squat"]
  },
  {
    "Name": "Default Shoulder",
    "Tags": ["shoulder"],
    "Exercises": [ "Military Press" ]
  },
  {
    "Name": "Default Cardio",
    "Tags": ["cardio"],
    "Exercises": ["Run"]
  }
]}